{
  "Status Code": 200,
  "Body": {
    "name": "service_orchestration_profilerTWjxX",
    "type": "X_000631_TDMGW",
    "orgId": "2550",
    "pBits": 5,
    "ipType": "IPv4",
    "vlanId": 810,
    "ESAMode": true,
    "RTPPort": 49152,
    "TimerT1": 500,
    "TimerT2": 4000,
    "ServerIP": "10.245.252.2",
    "category": "Voice Service",
    "Revertive": true,
    "DHCPFilter": true,
    "DNSPrimary": "192.168.33.10",
    "DTMFMethod": "InBand",
    "SwitchType": "None",
    "CountryCode": "US",
    "ProxyServer": "10.245.252.2",
    "RTPBasePort": 49152,
    "RTPCodec1st": "G.711MuLaw",
    "RTPCodec2nd": "G.711ALaw",
    "RTPCodec3rd": "G.729",
    "framingType": "IPoE",
    "DNSSecondary": "192.168.33.10",
    "RTPDscpValue": 46,
    "ReleaseTimer": 10,
    "RestartDelay": 1,
    "RetryTimeOut": 30,
    "OnHookPersist": true,
    "PacketRate1st": 10,
    "PacketRate2nd": 10,
    "PacketRate3rd": 10,
    "LocalHookFlash": true,
    "OffHookPersist": true,
    "RTPDscpOptions": 8,
    "SwitchTypeMGCP": "GENERIC",
    "TermPrefixH248": "TP",
    "TermPrefixMGCP": "aaln",
    "EphemeralTermID": "RTP",
    "OptionsInterval": 70,
    "ProxyServerPort": 5060,
    "UserAgentDomain": "CPE domain string. Applicable for SIP only",
    "ControlDscpValue": 46,
    "FlashHookPersist": true,
    "RTPDscpInputType": true,
    "PrimarySwitchType": "CS2000",
    "OptionsTimerSwitch": true,
    "RegistrationPeriod": 3600,
    "PrimaryGWController": "10.245.252.2",
    "SecondarySwitchType": "CS2000",
    "PrimaryCallMainAgent": "10.245.252.2",
    "ProxyServerSecondary": "10.245.252.2",
    "CallWaitingTonePrefix": "CallWaitingTone",
    "DistinctiveRingPrefix": "Bellcore-dr",
    "SecondaryGWController": "",
    "SilenceSuppression1st": true,
    "SilenceSuppression2nd": true,
    "SilenceSuppression3rd": true,
    "PrimaryCallBackupAgent": "10.245.252.2",
    "ProxyServerPortSecondary": 5060,
    "_id": "9351322c-bc71-4274-86d5-8a2d9fc298ed"
  }
}