{
  "Method": "POST",
  "URL": "http://gcs-stg.calix.com:8081/cc/service-orchestration-profile?orgId=50",
  "Params": null,
  "Body": {
    "name": "service_orchestration_profile2jKSpX",
    "orgId": "50",
    "category": "Video Service",
    "vlanId": 260,
    "productFamily": "GigaCenter",
    "bwProfile": "3d8d5b8e-8828-4f2e-8b45-24a7ad07cd1d",
    "mvrProfile": "aedaaae3-64e2-464f-bac5-e8a75d0ea2b4",
    "mode": "RG L2 Bridged",
    "dscp2PbitMap": true,
    "AnyPortAnyServiceEnabled": false,
    "APAS_EnableIPTV_SSID": false,
    "VLAN_Enable": true,
    "pBits": 4,
    "BridgedInterface": [
      "5GHz IPTV SSID",
      "LAN Port 2"
    ],
    "OUI_Enable": true,
    "OUI_FilterList": "2c:2d:2e:xx:xx:xx",
    "QueryInterval": 125,
    "MaxStreams": 0,
    "mcastFilterProfile": "b6ec6037-d293-44f0-8b14-dd351017a7fc"
  }
}